anything_world/__init__.py
anything_world/settings.py
anything_world/async_api/__init__.py
anything_world/async_api/api_client.py
anything_world/async_api/utils.py
anything_world/sync_api/__init__.py
anything_world/sync_api/api_client.py
anything_world/sync_api/utils.py
anything_world/utils/__init__.py
scripts/cli.py
anything_world-0.2.0.dist-info/LICENSE
anything_world-0.2.0.dist-info/METADATA
anything_world-0.2.0.dist-info/WHEEL
anything_world-0.2.0.dist-info/entry_points.txt
anything_world-0.2.0.dist-info/top_level.txt
anything_world-0.2.0.dist-info/RECORD
