Metadata-Version: 2.1
Name: anything_world
Version: 0.2.0
Summary: Anything World API wrapper library and CLI
Author-email: Anything World <support@anything.world>
License: MIT
Project-URL: Homepage, https://anything.world
Classifier: License :: OSI Approved :: MIT License
Classifier: Programming Language :: Python :: 3
Requires-Python: >=3.7
License-File: LICENSE
Requires-Dist: python-dotenv==1.0.0
Requires-Dist: requests==2.28.2
Requires-Dist: pytest==7.2.2
Requires-Dist: pytest-asyncio==0.21.0
Requires-Dist: aiohttp==3.8.4
Requires-Dist: aiofiles==23.2.1
Requires-Dist: fire==0.5.0
